{"d09ab8c638634a8300b49d60f8b02178":{"statistic":{"failed":0,"broken":0,"skipped":0,"passed":1,"unknown":0,"total":1},"items":[{"uid":"d9c3a7af00c41308","reportUrl":"https://denysvoskovets.github.io/example-playwright-python/6//#testresult/d9c3a7af00c41308","status":"passed","time":{"start":1755320450400,"stop":1755320453474,"duration":3074}}]},"9c2077077f4bac32801f337d4f8e3280":{"statistic":{"failed":0,"broken":0,"skipped":0,"passed":1,"unknown":0,"total":1},"items":[{"uid":"d1fd26739933a7c1","reportUrl":"https://denysvoskovets.github.io/example-playwright-python/6//#testresult/d1fd26739933a7c1","status":"passed","time":{"start":1755320440249,"stop":1755320442306,"duration":2057}}]},"88f3c445b8ac9893e997e220add87ef2":{"statistic":{"failed":0,"broken":0,"skipped":0,"passed":1,"unknown":0,"total":1},"items":[{"uid":"8254964ffe79ab1","reportUrl":"https://denysvoskovets.github.io/example-playwright-python/6//#testresult/8254964ffe79ab1","status":"passed","time":{"start":1755320442648,"stop":1755320444102,"duration":1454}}]},"6dc344baf87e735614f3e91a08a31e03":{"statistic":{"failed":0,"broken":0,"skipped":0,"passed":1,"unknown":0,"total":1},"items":[{"uid":"831a865fecb9b894","reportUrl":"https://denysvoskovets.github.io/example-playwright-python/6//#testresult/831a865fecb9b894","status":"passed","time":{"start":1755320445764,"stop":1755320447040,"duration":1276}}]},"e234db8e2ee179c68b847673fe56abaa":{"statistic":{"failed":0,"broken":0,"skipped":0,"passed":1,"unknown":0,"total":1},"items":[{"uid":"838a4dd04850b008","reportUrl":"https://denysvoskovets.github.io/example-playwright-python/6//#testresult/838a4dd04850b008","status":"passed","time":{"start":1755320453813,"stop":1755320456679,"duration":2866}}]},"14cdbf4de61a50a784a42bb748c44751":{"statistic":{"failed":0,"broken":0,"skipped":0,"passed":1,"unknown":0,"total":1},"items":[{"uid":"14b4f2da20bd9384","reportUrl":"https://denysvoskovets.github.io/example-playwright-python/6//#testresult/14b4f2da20bd9384","status":"passed","time":{"start":1755320444330,"stop":1755320445519,"duration":1189}}]},"a9a58e3849eceb1512b38f8db48dacb8":{"statistic":{"failed":0,"broken":0,"skipped":0,"passed":1,"unknown":0,"total":1},"items":[{"uid":"1c615a07c27046d2","reportUrl":"https://denysvoskovets.github.io/example-playwright-python/6//#testresult/1c615a07c27046d2","status":"passed","time":{"start":1755320448137,"stop":1755320450039,"duration":1902}}]}}